PooledProcessMixIn.py
setup.py
PooledProcessMixIn.egg-info/PKG-INFO
PooledProcessMixIn.egg-info/SOURCES.txt
PooledProcessMixIn.egg-info/dependency_links.txt
PooledProcessMixIn.egg-info/top_level.txt